<annotation>
	<folder>images</folder>
	<filename>Japan_011879.jpg</filename>
	<size>
		<width>600</width>
		<height>600</height>
		<depth>3</depth>
	</size>
	<segmented>0</segmented>
	<object>
		<name>D20</name>
		<pose>Unspecified</pose>
		<truncated>1</truncated>
		<difficult>0</difficult>
		<bndbox>
			<xmin>418</xmin>
			<ymin>367</ymin>
			<xmax>600</xmax>
			<ymax>599</ymax>
		</bndbox>
	</object>
	<object>
		<name>D50</name>
		<pose>Unspecified</pose>
		<truncated>1</truncated>
		<difficult>0</difficult>
		<bndbox>
			<xmin>163</xmin>
			<ymin>549</ymin>
			<xmax>295</xmax>
			<ymax>600</ymax>
		</bndbox>
	</object>
	<object>
		<name>D50</name>
		<pose>Unspecified</pose>
		<truncated>0</truncated>
		<difficult>0</difficult>
		<bndbox>
			<xmin>18</xmin>
			<ymin>463</ymin>
			<xmax>84</xmax>
			<ymax>491</ymax>
		</bndbox>
	</object>
</annotation>